botobot/__init__.py
botobot/agent.py
botobot/main.py
botobot-0.1.1.dist-info/METADATA
botobot-0.1.1.dist-info/WHEEL
botobot-0.1.1.dist-info/entry_points.txt
botobot-0.1.1.dist-info/RECORD
